<annotation>
	<folder>img</folder>
	<filename>cmnd_Mai_Th_Triu.jpg</filename>
	<path>/home/whoisltd/Desktop/img/cmnd_Mai_Th_Triu.jpg</path>
	<source>
		<database>Unknown</database>
	</source>
	<size>
		<width>313</width>
		<height>206</height>
		<depth>3</depth>
	</size>
	<segmented>0</segmented>
	<object>
		<name>num</name>
		<pose>Unspecified</pose>
		<truncated>0</truncated>
		<difficult>0</difficult>
		<bndbox>
			<xmin>158</xmin>
			<ymin>48</ymin>
			<xmax>242</xmax>
			<ymax>66</ymax>
		</bndbox>
	</object>
	<object>
		<name>name</name>
		<pose>Unspecified</pose>
		<truncated>0</truncated>
		<difficult>0</difficult>
		<bndbox>
			<xmin>162</xmin>
			<ymin>67</ymin>
			<xmax>273</xmax>
			<ymax>86</ymax>
		</bndbox>
	</object>
	<object>
		<name>birth</name>
		<pose>Unspecified</pose>
		<truncated>0</truncated>
		<difficult>0</difficult>
		<bndbox>
			<xmin>189</xmin>
			<ymin>105</ymin>
			<xmax>256</xmax>
			<ymax>124</ymax>
		</bndbox>
	</object>
	<object>
		<name>hometown</name>
		<pose>Unspecified</pose>
		<truncated>0</truncated>
		<difficult>0</difficult>
		<bndbox>
			<xmin>181</xmin>
			<ymin>123</ymin>
			<xmax>286</xmax>
			<ymax>141</ymax>
		</bndbox>
	</object>
	<object>
		<name>addr</name>
		<pose>Unspecified</pose>
		<truncated>0</truncated>
		<difficult>0</difficult>
		<bndbox>
			<xmin>221</xmin>
			<ymin>158</ymin>
			<xmax>279</xmax>
			<ymax>177</ymax>
		</bndbox>
	</object>
	<object>
		<name>addr</name>
		<pose>Unspecified</pose>
		<truncated>0</truncated>
		<difficult>0</difficult>
		<bndbox>
			<xmin>106</xmin>
			<ymin>177</ymin>
			<xmax>286</xmax>
			<ymax>196</ymax>
		</bndbox>
	</object>
</annotation>
