<annotation>
	<folder>Hoang</folder>
	<filename>cmnd_Ho_Mi_1_001.jpg</filename>
	<path>/home/phan.huy.hoang/workspace/framgia/reid_card/data/total_real_img/Hoang/cmnd_Ho_Mi_1_001.jpg</path>
	<source>
		<database>Unknown</database>
	</source>
	<size>
		<width>373</width>
		<height>254</height>
		<depth>3</depth>
	</size>
	<segmented>0</segmented>
	<object>
		<name>top_left</name>
		<pose>Unspecified</pose>
		<truncated>1</truncated>
		<difficult>0</difficult>
		<bndbox>
			<xmin>1</xmin>
			<ymin>14</ymin>
			<xmax>28</xmax>
			<ymax>37</ymax>
		</bndbox>
	</object>
	<object>
		<name>top_right</name>
		<pose>Unspecified</pose>
		<truncated>0</truncated>
		<difficult>0</difficult>
		<bndbox>
			<xmin>340</xmin>
			<ymin>10</ymin>
			<xmax>368</xmax>
			<ymax>32</ymax>
		</bndbox>
	</object>
	<object>
		<name>bottom_right</name>
		<pose>Unspecified</pose>
		<truncated>1</truncated>
		<difficult>0</difficult>
		<bndbox>
			<xmin>340</xmin>
			<ymin>232</ymin>
			<xmax>372</xmax>
			<ymax>254</ymax>
		</bndbox>
	</object>
	<object>
		<name>bottom_left</name>
		<pose>Unspecified</pose>
		<truncated>1</truncated>
		<difficult>0</difficult>
		<bndbox>
			<xmin>1</xmin>
			<ymin>229</ymin>
			<xmax>25</xmax>
			<ymax>253</ymax>
		</bndbox>
	</object>
</annotation>
