<annotation>
	<folder>img</folder>
	<filename>cmnd_hng_11_001.jpg</filename>
	<path>/home/whoisltd/Desktop/img/cmnd_hng_11_001.jpg</path>
	<source>
		<database>Unknown</database>
	</source>
	<size>
		<width>348</width>
		<height>218</height>
		<depth>3</depth>
	</size>
	<segmented>0</segmented>
	<object>
		<name>num</name>
		<pose>Unspecified</pose>
		<truncated>0</truncated>
		<difficult>0</difficult>
		<bndbox>
			<xmin>180</xmin>
			<ymin>52</ymin>
			<xmax>276</xmax>
			<ymax>70</ymax>
		</bndbox>
	</object>
	<object>
		<name>name</name>
		<pose>Unspecified</pose>
		<truncated>0</truncated>
		<difficult>0</difficult>
		<bndbox>
			<xmin>161</xmin>
			<ymin>71</ymin>
			<xmax>329</xmax>
			<ymax>96</ymax>
		</bndbox>
	</object>
	<object>
		<name>birth</name>
		<pose>Unspecified</pose>
		<truncated>0</truncated>
		<difficult>0</difficult>
		<bndbox>
			<xmin>213</xmin>
			<ymin>117</ymin>
			<xmax>291</xmax>
			<ymax>135</ymax>
		</bndbox>
	</object>
	<object>
		<name>hometown</name>
		<pose>Unspecified</pose>
		<truncated>0</truncated>
		<difficult>0</difficult>
		<bndbox>
			<xmin>227</xmin>
			<ymin>135</ymin>
			<xmax>296</xmax>
			<ymax>154</ymax>
		</bndbox>
	</object>
	<object>
		<name>hometown</name>
		<pose>Unspecified</pose>
		<truncated>0</truncated>
		<difficult>0</difficult>
		<bndbox>
			<xmin>148</xmin>
			<ymin>153</ymin>
			<xmax>298</xmax>
			<ymax>176</ymax>
		</bndbox>
	</object>
	<object>
		<name>addr</name>
		<pose>Unspecified</pose>
		<truncated>0</truncated>
		<difficult>0</difficult>
		<bndbox>
			<xmin>237</xmin>
			<ymin>174</ymin>
			<xmax>325</xmax>
			<ymax>194</ymax>
		</bndbox>
	</object>
	<object>
		<name>addr</name>
		<pose>Unspecified</pose>
		<truncated>0</truncated>
		<difficult>0</difficult>
		<bndbox>
			<xmin>143</xmin>
			<ymin>193</ymin>
			<xmax>297</xmax>
			<ymax>214</ymax>
		</bndbox>
	</object>
</annotation>
