<annotation>
	<folder>img</folder>
	<filename>cmnd_H_Th_Thu_Tho_.jpg</filename>
	<path>/home/whoisltd/Desktop/img/cmnd_H_Th_Thu_Tho_.jpg</path>
	<source>
		<database>Unknown</database>
	</source>
	<size>
		<width>370</width>
		<height>236</height>
		<depth>3</depth>
	</size>
	<segmented>0</segmented>
	<object>
		<name>num</name>
		<pose>Unspecified</pose>
		<truncated>0</truncated>
		<difficult>0</difficult>
		<bndbox>
			<xmin>195</xmin>
			<ymin>54</ymin>
			<xmax>293</xmax>
			<ymax>75</ymax>
		</bndbox>
	</object>
	<object>
		<name>name</name>
		<pose>Unspecified</pose>
		<truncated>0</truncated>
		<difficult>0</difficult>
		<bndbox>
			<xmin>183</xmin>
			<ymin>77</ymin>
			<xmax>340</xmax>
			<ymax>102</ymax>
		</bndbox>
	</object>
	<object>
		<name>birth</name>
		<pose>Unspecified</pose>
		<truncated>0</truncated>
		<difficult>0</difficult>
		<bndbox>
			<xmin>233</xmin>
			<ymin>119</ymin>
			<xmax>306</xmax>
			<ymax>141</ymax>
		</bndbox>
	</object>
	<object>
		<name>hometown</name>
		<pose>Unspecified</pose>
		<truncated>0</truncated>
		<difficult>0</difficult>
		<bndbox>
			<xmin>227</xmin>
			<ymin>143</ymin>
			<xmax>334</xmax>
			<ymax>164</ymax>
		</bndbox>
	</object>
	<object>
		<name>hometown</name>
		<pose>Unspecified</pose>
		<truncated>0</truncated>
		<difficult>0</difficult>
		<bndbox>
			<xmin>147</xmin>
			<ymin>164</ymin>
			<xmax>328</xmax>
			<ymax>185</ymax>
		</bndbox>
	</object>
	<object>
		<name>addr</name>
		<pose>Unspecified</pose>
		<truncated>0</truncated>
		<difficult>0</difficult>
		<bndbox>
			<xmin>238</xmin>
			<ymin>184</ymin>
			<xmax>354</xmax>
			<ymax>204</ymax>
		</bndbox>
	</object>
	<object>
		<name>addr</name>
		<pose>Unspecified</pose>
		<truncated>0</truncated>
		<difficult>0</difficult>
		<bndbox>
			<xmin>147</xmin>
			<ymin>203</ymin>
			<xmax>328</xmax>
			<ymax>224</ymax>
		</bndbox>
	</object>
</annotation>
